Workbook

Sheet Introduction
D2: Introduction & Information
A5: All previous financial data were taked from Lloyds Bank Annual Reports - All publicly available
A7: Purpose of creating this model is purely for personal development & practice & curiosity - All adjusted numbers and assumptions are based on personal opinion
A9: MODEL AND FINANCIAL DATA DO NOT CONTAIN ANY SENSITIVE DATA & FINANCIAL ADVICE
A11: Please do not publish the model anywhere. But if you are interested in using or developing the model for your personal development & curiosity, feel free
A13: If you`d like to discuss the model or have any questions about assumptions & formulas, please contact me
A15: Enjoy Exploring!
A17: Best Regards,
A18: Berk Tansuker
A20: Github
A21: LinkedIn
A22: E-Mail

Sheet 00_Control
A1: Category | B1: Parameter | C1: Value | D1: Comment
A2: Scenario | B2: Scenario Selector | C2: Up100 | D2: Base / Up100 / Down100
A3: Scenario | B3: Shock (bps) | C3: =IF(C2="Base",0,IF(C2="Up100",100,IF(C2="Down100",-100,0))) -> 100 | D3: Auto-calculated
A4: Scenario | B4: Shock | C4: =C3/10000 -> 0.01 | D4: Convert bps to %
A5: Scenario | B5: Selected Year | C5: 2025 | D5: 2016 to 2025
A6: Assets_Betas | B6: Loan_Beta | C6: 0.8 | D6: % pass-through
A7: Liabilitiy_Betas | B7: Deposit_Beta | C7: 0.35 | D7: Sticky deposits
A8: Liabilitiy_Betas | B8: Wholesale_Funding_Beta | C8: 0.9 | D8: Market-linked
A9: Repricing_12M | B9: Loans_Repricing | C9: 0.6 | D9: % reprices within 1y
A10: Repricing_12M | B10: Deposits_Repricing | C10: 0.5 | D10: % reprices within 1y
A11: Repricing_12M | B11: Funding_Repricing | C11: 0.8 | D11: % reprices within 1y
A12: P&L | B12: Tax Rate | C12: ='01_RawData'!K20 -> 0.23 | D12: RawData-linked
A13: Hedge Factor | B13: Hedge_Adjustment | C13: 0.6 | D13: Assumption

Sheet 01_RawData
A1: Line Item | B1: 2016 | C1: 2017 | D1: 2018 | E1: 2019 | F1: 2020 | G1: 2021 | H1: 2022 | I1: 2023 | J1: 2024 | K1: 2025 | L1: Source Note
A2: Net Interest Income | B2: 9274 | C2: 10912 | D2: 13396 | E2: 10180 | F2: 10749 | G2: 9366 | H2: 13957 | I2: 13298 | J2: 12277 | K2: 13230 | L2: Annual Report - Direct
A3: Interest Income | B3: 16620 | C3: 16006 | D3: 16349 | E3: 16861 | F3: 14306 | G3: 13258 | H3: 17645 | I3: 28051 | J3: 31288 | K3: 30749 | L3: Annual Report - Direct
A4: Interest Expense | B4: 7346 | C4: 5094 | D4: 2953 | E4: 6681 | F4: 3557 | G4: 3892 | H4: 3688 | I4: 14753 | J4: 19011 | K4: 17519 | L4: Annual Report - Direct
A5: Underlying Net Interest Income | B5: 11435 | C5: 12320 | D5: 12714 | E5: 12377 | F5: 10773 | G5: 11163 | H5: 13172 | I5: 13765 | J5: 12845 | K5: 13635 | L5: Annual Report - Direct
A6: Loans - End Balance | B6: 450000 | C6: 456000 | D6: 444000 | E6: 440000 | F6: 440000 | G6: 449000 | H6: 454900 | I6: 449700 | J6: 459100 | K6: 481000 | L6: Annual Report - Direct
A7: Loans - Beginning Balance | B7: 455000 | C7: 450000 | D7: 456000 | E7: 444000 | F7: 440000 | G7: 440000 | H7: 449000 | I7: 454900 | J7: 449700 | K7: 459100 | L7: Annual Report - Direct
A8: Loans - Average | B8: =(B6+B7)/2 -> 452500 | C8: =(C6+C7)/2 -> 453000 | D8: =(D6+D7)/2 -> 450000 | E8: =(E6+E7)/2 -> 442000 | F8: =(F6+F7)/2 -> 440000 | G8: =(G6+G7)/2 -> 444500 | H8: =(H6+H7)/2 -> 451950 | I8: =(I6+I7)/2 -> 452300 | ... K8: =(K6+K7)/2 -> 470050 | L8: Calculated from Annual Reports Data
A9: Customer Deposits - End | B9: 413000 | C9: 416000 | D9: 416000 | E9: 412000 | F9: 451000 | G9: 476000 | H9: 475300 | I9: 471400 | J9: 482700 | K9: 496500 | L9: Annual Report - Direct
A10: Customer Deposits - Beginning | B10: 418000 | C10: 413000 | D10: 416000 | E10: 416000 | F10: 412000 | G10: 451000 | H10: 476000 | I10: 475300 | J10: 471400 | K10: 482700 | L10: Annual Report - Direct
A11: Customer Deposits - Average | B11: =(B9+B10)/2 -> 415500 | C11: =(C9+C10)/2 -> 414500 | D11: =(D9+D10)/2 -> 416000 | E11: =(E9+E10)/2 -> 414000 | F11: =(F9+F10)/2 -> 431500 | G11: =(G9+G10)/2 -> 463500 | H11: =(H9+H10)/2 -> 475650 | I11: =(I9+I10)/2 -> 473350 | ... K11: =(K9+K10)/2 -> 489600 | L11: Calculated from Annual Reports Data
A12: Wholesale Funding - End | B12: 111000 | C12: 101000 | D12: 123000 | E12: 124000 | F12: 109400 | G12: 91400 | H12: 100300 | I12: 98700 | J12: 92500 | K12: 99400 | L12: Annual Report - Direct
A13: Wholesale Funding - Beginning | B13: 120000 | C13: 111000 | D13: 101000 | E13: 123000 | F13: 124000 | G13: 109400 | H13: 91400 | I13: 100300 | J13: 98700 | K13: 92500 | L13: Annual Report - Direct
A14: Wholesale Funding - Average | B14: =(B12+B13)/2 -> 115500 | C14: =(C12+C13)/2 -> 106000 | D14: =(D12+D13)/2 -> 112000 | E14: =(E12+E13)/2 -> 123500 | F14: =(F12+F13)/2 -> 116700 | G14: =(G12+G13)/2 -> 100400 | H14: =(H12+H13)/2 -> 95850 | I14: =(I12+I13)/2 -> 99500 | ... K14: =(K12+K13)/2 -> 95950 | L14: Calculated from Annual Reports Data
A15: Average Interest-Earning Assets (AIEA) | B15: 436000 | C15: 435000 | D15: 436000 | E15: 435000 | F15: 435000 | G15: 445000 | H15: 452000 | I15: 453300 | J15: 451200 | K15: 462900 | L15: Annual Report - Direct
A16: Total Interest-Bearing Funding - Average | B16: =B11+B14 -> 531000 | C16: =C11+C14 -> 520500 | D16: =D11+D14 -> 528000 | E16: =E11+E14 -> 537500 | F16: =F11+F14 -> 548200 | G16: =G11+G14 -> 563900 | H16: =H11+H14 -> 571500 | I16: =I11+I14 -> 572850 | ... K16: =K11+K14 -> 585550 | L16: Calculated from Annual Reports Data
A17: Profit Before Tax | B17: 4238 | C17: 5275 | D17: 5960 | E17: 4393 | F17: 1226 | G17: 6902 | H17: 6928 | I17: 7503 | J17: 5971 | K17: 6661 | L17: Annual Report - Direct
A18: Tax Expense | B18: 1724 | C18: 1626 | D18: 1454 | E18: 1387 | F18: -161 | G18: 1017 | H18: 1373 | I18: 1985 | J18: 1494 | K18: 1904 | L18: Annual Report - Direct
A19: Effective Tax Rate | B19: =B18/B17 -> 0.40679566 | C19: =C18/C17 -> 0.30824645 | D19: =D18/D17 -> 0.24395973 | E19: =E18/E17 -> 0.31572957 | F19: =F18/F17 -> -0.13132137 | G19: =G18/G17 -> 0.14734859 | H19: =H18/H17 -> 0.19818129 | I19: =I18/I17 -> 0.26456084 | ... K19: =K18/K17 -> 0.28584297 | L19: Calculated from Annual Reports Data
A20: Stabilized Tax Rate - Historical Average | B20: 0.23 | C20: 0.23 | D20: 0.23 | E20: 0.23 | F20: 0.23 | G20: 0.23 | H20: 0.23 | I20: 0.23 | J20: 0.23 | K20: 0.23 | L20: Average of 10 years
A21: Wholesale Funding Cost | B21: =B4/B14 -> 0.063601732 | C21: =C4/C14 -> 0.048056604 | D21: =D4/D14 -> 0.026366071 | E21: =E4/E14 -> 0.054097166 | F21: =F4/F14 -> 0.030479863 | G21: =G4/G14 -> 0.03876494 | H21: =H4/H14 -> 0.038476787 | I21: =I4/I14 -> 0.14827136 | ... K21: =K4/K14 -> 0.18258468 | L21: Calculated from Annual Reports Data
A22: Loan Yield Check | B22: =B3/B8 -> 0.036729282 | C22: =C3/C8 -> 0.035333333 | D22: =D3/D8 -> 0.036331111 | E22: =E3/E8 -> 0.038147059 | F22: =F3/F8 -> 0.032513636 | G22: =G3/G8 -> 0.029826772 | H22: =H3/H8 -> 0.039041929 | I22: =I3/I8 -> 0.062018572 | ... K22: =K3/K8 -> 0.065416445 | L22: Calculated from Annual Reports Data
A23: Total Cost of Funding | B23: =B4/B16 -> 0.013834275 | C23: =C4/C16 -> 0.0097867435 | D23: =D4/D16 -> 0.005592803 | E23: =E4/E16 -> 0.012429767 | F23: =F4/F16 -> 0.0064885078 | G23: =G4/G16 -> 0.006901933 | H23: =H4/H16 -> 0.0064531934 | I23: =I4/I16 -> 0.025753688 | J23: =J4/J16 -> 0.033198289 | K23: =K4/(K11+K14) -> 0.02991888 | L23: Calculated from Annual Reports Data
A24: Underlying NIM | B24: =B5/B15 -> 0.026227064 | C24: =C5/C15 -> 0.028321839 | D24: =D5/D15 -> 0.02916055 | E24: =E5/E15 -> 0.028452874 | F24: =F5/F15 -> 0.024765517 | G24: =G5/G15 -> 0.025085393 | H24: =H5/H15 -> 0.029141593 | I24: =I5/I15 -> 0.030366203 | ... K24: =K5/K15 -> 0.029455606 | L24: Calculated from Annual Reports Data
A25: Statutory NIM | B25: =B2/B15 -> 0.021270642 | C25: =C2/C15 -> 0.025085057 | D25: =D2/D15 -> 0.030724771 | E25: =E2/E15 -> 0.023402299 | F25: =F2/F15 -> 0.024710345 | G25: =G2/G15 -> 0.021047191 | H25: =H2/H15 -> 0.030878319 | I25: =I2/I15 -> 0.029335981 | ... K25: =K2/K15 -> 0.028580687 | L25: Calculated from Annual Reports Data
A26: Reported Banking NIM | B26: 0.0271 | C26: 0.0286 | D26: 0.0293 | E26: 0.0288 | F26: 0.0252 | G26: 0.0254 | H26: 0.0294 | I26: 0.0311 | J26: 0.0295 | K26: 0.0306 | L26: Annual Report - Direct
A27: Implied Banking NII | B27: =B26*B15 -> 11815.6 | C27: =C26*C15 -> 12441 | D27: =D26*D15 -> 12774.8 | E27: =E26*E15 -> 12528 | F27: =F26*F15 -> 10962 | G27: =G26*G15 -> 11303 | H27: =H26*H15 -> 13288.8 | I27: =I26*I15 -> 14097.63 | ... K27: =K26*K15 -> 14164.74 | L27: Calculated from Annual Reports Data
A28: NII Recon / Adjustment | B28: =B27-B5 -> 380.6 | C28: =C27-C5 -> 121 | D28: =D27-D5 -> 60.8 | E28: =E27-E5 -> 151 | F28: =F27-F5 -> 189 | G28: =G27-G5 -> 140 | H28: =H27-H5 -> 116.8 | I28: =I27-I5 -> 332.63 | ... K28: =K27-K5 -> 529.74 | L28: Calculated from Annual Reports Data

Sheet 02_Scenarios
A1: Metric | B1: Value
A2: Selected Shock (%) | B2: =INDEX('00_Control'!$C:$C, MATCH("Shock ", '00_Control'!$B:$B, 0)) -> 0.01
A3: Selected Year | B3: =INDEX('00_Control'!$C:$C, MATCH("Selected Year", '00_Control'!$B:$B, 0)) -> 2025
A4: Year_Col | B4: =MATCH($B$3, '01_RawData'!$B$1:$K$1, 0) -> 10
A5: --- BASE INPUTS ---
A6: Loans Avg | B6: {=INDEX('01_RawData'!$B:$K, MATCH("Loans - Average", '01_RawData'!$A:$A, 0), $B$4)} -> 470050
A7: Deposits Avg | B7: {=INDEX('01_RawData'!$B:$K, MATCH("Customer Deposits - Average", '01_RawData'!$A:$A, 0), $B$4)} -> 489600
A8: Funding Avg | B8: {=INDEX('01_RawData'!$B:$K, MATCH("Wholesale Funding - Average", '01_RawData'!$A:$A, 0), $B$4)} -> 95950
A9: AIEA | B9: {=INDEX('01_RawData'!$B:$K, MATCH("Average Interest-Earning Assets (AIEA)", '01_RawData'!$A:$A, 0), $B$4)} -> 462900
A10: Base NII (Model) | B10: {=INDEX('01_RawData'!$B:$K, MATCH("Implied Banking NII", '01_RawData'!$A:$A, 0), $B$4)} -> 14164.74
A11: Base NIM (Model) | B11: {=INDEX('01_RawData'!$B:$K, MATCH("Reported Banking NIM", '01_RawData'!$A:$A, 0), $B$4)} -> 0.0306
A12: Tax Rate | B12: =INDEX('00_Control'!$C:$C, MATCH("Tax Rate", '00_Control'!$B:$B, 0)) -> 0.23
A13: --- PARAMETERS ---
A14: Loan Beta | B14: =INDEX('00_Control'!$C:$C, MATCH("Loan_Beta", '00_Control'!$B:$B, 0)) -> 0.8
A15: Deposit Beta | B15: =INDEX('00_Control'!$C:$C, MATCH("Deposit_Beta", '00_Control'!$B:$B, 0)) -> 0.35
A16: Funding Beta | B16: =INDEX('00_Control'!$C:$C, MATCH("Wholesale_Funding_Beta", '00_Control'!$B:$B, 0)) -> 0.9
A17: Loans Repricing | B17: =INDEX('00_Control'!$C:$C, MATCH("Loans_Repricing", '00_Control'!$B:$B, 0)) -> 0.6
A18: Deposits Repricing | B18: =INDEX('00_Control'!$C:$C, MATCH("Deposits_Repricing", '00_Control'!$B:$B, 0)) -> 0.5
A19: Funding Repricing | B19: =INDEX('00_Control'!$C:$C, MATCH("Funding_Repricing", '00_Control'!$B:$B, 0)) -> 0.8
A20: --- SHOCK CALCULATION ---
A21: Delta Loan Income | B21: =B2*B6*B14*B17 -> 2256.24
A22: Delta Deposit Expense | B22: =B2*B7*B15*B18 -> 856.8
A23: Delta Funding Expense | B23: =B2*B8*B16*B19 -> 690.84
A24: Delta NII | B24: =B21-B22-B23 -> 708.6
A25: --- OUTPUTS ---
A26: New NII | B26: =B10+B24 -> 14873.34
A27: New NIM | B27: =B26/B9 -> 0.032130784
A28: Delta NIM (bps) | B28: =(B27-B11)*10000 -> 15.307842
A29: Delta Net Income | B29: =B24*(1-'00_Control'!C12) -> 545.622

Sheet 03_Summary
A1: Year | B1: Base NIM | C1: Base NII | D1: ΔNII (+100bps) | E1: ΔNIM (+100bps, bps) | F1: ΔNI (+100bps) | G1: ΔNII (-100bps) | H1: ΔNIM (-100bps, bps) | I1: ΔNI (-100bps) | J1: Adj ΔNII | K1: Adj ΔNIM | L1: Adj ΔNI
A2: 2016 | B2: =INDEX('01_RawData'!$B:$K, MATCH("Reported Banking NIM", '01_RawData'!$A:$A, 0), MATCH($A2, '01_RawData'!$B$1:$K$1, 0)) -> 0.0271 | C2: =INDEX('01_RawData'!$B:$K, MATCH("Implied Banking NII", '01_RawData'!$A:$A, 0), MATCH($A2, '01_RawData'!$B$1:$K$1, 0)) -> 11815.6 | D2: =(INDEX('01_RawData'!$B:$K,MATCH("Loans - Average",'01_RawData'!$A:$A,0),MATCH($A2,'01_RawData'!$B$1:$K$1,0))*INDEX('00_Control'!$C:$C,MATCH("Loan_Beta",'00_Control'!$B:$B,0))*INDEX('00_Control'!$C:$C,MATCH("Loans_Repricing",'00_Control'!$B:$B,0))*0.01)-(INDEX('01_RawData'!$B:$K,MATCH("Customer Deposits - Average",'01_RawData'!$A:$A,0),MATCH($A2,'01_RawData'!$B$1:$K$1,0))*INDEX('00_Control'!$C:$C,MATCH("Deposit_Beta",'00_Control'!$B:$B,0)) *INDEX('00_Control'!$C:$C,MATCH("Deposits_Repricing",'00_Control'!$B:$B,0))*0.01)-(INDEX('01_RawData'!$B:$K,MATCH("Wholesale Funding - Average",'01_RawData'!$A:$A,0),MATCH($A2,'01_RawData'!$B$1:$K$1,0))*INDEX('00_Control'!$C:$C,MATCH("Wholesale_Funding_Beta",'00_Control'!$B:$B,0)) *INDEX('00_Control'!$C:$C,MATCH("Funding_Repricing",'00_Control'!$B:$B,0)) *0.01) -> 613.275 | E2: =((($C2 + $D2) /INDEX('01_RawData'!$B:$K,MATCH("Average Interest-Earning Assets (AIEA)",'01_RawData'!$A:$A,0),MATCH($A2,'01_RawData'!$B$1:$K$1,0)))- $B2) * 10000 -> 14.06594 | F2: =D2 * (1 - INDEX('00_Control'!$C:$C, MATCH("Tax Rate", '00_Control'!$B:$B, 0))) -> 472.22175 | G2: =-D2 -> -613.275 | H2: =((($C2 + $G2) /INDEX('01_RawData'!$B:$K,MATCH("Average Interest-Earning Assets (AIEA)",'01_RawData'!$A:$A,0),MATCH($A2,'01_RawData'!$B$1:$K$1,0)))- $B2) * 10000 -> -14.06594 | I2: =-F2 -> -472.22175 | J2: =D2 * INDEX('00_Control'!$C:$C, MATCH("Hedge_Adjustment", '00_Control'!$B:$B, 0)) -> 367.965 | K2: =($J2 / INDEX('01_RawData'!$B:$K,MATCH("Average Interest-Earning Assets (AIEA)", '01_RawData'!$A:$A, 0),MATCH($A2, '01_RawData'!$B$1:$K$1, 0))) * 10000 -> 8.4395642 | L2: =F2 * INDEX('00_Control'!$C:$C, MATCH("Hedge_Adjustment", '00_Control'!$B:$B, 0)) -> 283.33305
A3: 2017 | B3: =INDEX('01_RawData'!$B:$K, MATCH("Reported Banking NIM", '01_RawData'!$A:$A, 0), MATCH($A3, '01_RawData'!$B$1:$K$1, 0)) -> 0.0286 | C3: =INDEX('01_RawData'!$B:$K, MATCH("Implied Banking NII", '01_RawData'!$A:$A, 0), MATCH($A3, '01_RawData'!$B$1:$K$1, 0)) -> 12441 | D3: =(INDEX('01_RawData'!$B:$K,MATCH("Loans - Average",'01_RawData'!$A:$A,0),MATCH($A3,'01_RawData'!$B$1:$K$1,0))*INDEX('00_Control'!$C:$C,MATCH("Loan_Beta",'00_Control'!$B:$B,0))*INDEX('00_Control'!$C:$C,MATCH("Loans_Repricing",'00_Control'!$B:$B,0))*0.01)-(INDEX('01_RawData'!$B:$K,MATCH("Customer Deposits - Average",'01_RawData'!$A:$A,0),MATCH($A3,'01_RawData'!$B$1:$K$1,0))*INDEX('00_Control'!$C:$C,MATCH("Deposit_Beta",'00_Control'!$B:$B,0)) *INDEX('00_Control'!$C:$C,MATCH("Deposits_Repricing",'00_Control'!$B:$B,0))*0.01)-(INDEX('01_RawData'!$B:$K,MATCH("Wholesale Funding - Average",'01_RawData'!$A:$A,0),MATCH($A3,'01_RawData'!$B$1:$K$1,0))*INDEX('00_Control'!$C:$C,MATCH("Wholesale_Funding_Beta",'00_Control'!$B:$B,0)) *INDEX('00_Control'!$C:$C,MATCH("Funding_Repricing",'00_Control'!$B:$B,0)) *0.01) -> 685.825 | E3: =((($C3 + $D3) /INDEX('01_RawData'!$B:$K,MATCH("Average Interest-Earning Assets (AIEA)",'01_RawData'!$A:$A,0),MATCH($A3,'01_RawData'!$B$1:$K$1,0)))- $B3) * 10000 -> 15.766092 | F3: =D3 * (1 - INDEX('00_Control'!$C:$C, MATCH("Tax Rate", '00_Control'!$B:$B, 0))) -> 528.08525 | G3: =-D3 -> -685.825 | H3: =((($C3 + $G3) /INDEX('01_RawData'!$B:$K,MATCH("Average Interest-Earning Assets (AIEA)",'01_RawData'!$A:$A,0),MATCH($A3,'01_RawData'!$B$1:$K$1,0)))- $B3) * 10000 -> -15.766092 | I3: =-F3 -> -528.08525 | J3: =D3 * INDEX('00_Control'!$C:$C, MATCH("Hedge_Adjustment", '00_Control'!$B:$B, 0)) -> 411.495 | K3: =($J3 / INDEX('01_RawData'!$B:$K,MATCH("Average Interest-Earning Assets (AIEA)", '01_RawData'!$A:$A, 0),MATCH($A3, '01_RawData'!$B$1:$K$1, 0))) * 10000 -> 9.4596552 | L3: =F3 * INDEX('00_Control'!$C:$C, MATCH("Hedge_Adjustment", '00_Control'!$B:$B, 0)) -> 316.85115
A4: 2018 | B4: =INDEX('01_RawData'!$B:$K, MATCH("Reported Banking NIM", '01_RawData'!$A:$A, 0), MATCH($A4, '01_RawData'!$B$1:$K$1, 0)) -> 0.0293 | C4: =INDEX('01_RawData'!$B:$K, MATCH("Implied Banking NII", '01_RawData'!$A:$A, 0), MATCH($A4, '01_RawData'!$B$1:$K$1, 0)) -> 12774.8 | D4: =(INDEX('01_RawData'!$B:$K,MATCH("Loans - Average",'01_RawData'!$A:$A,0),MATCH($A4,'01_RawData'!$B$1:$K$1,0))*INDEX('00_Control'!$C:$C,MATCH("Loan_Beta",'00_Control'!$B:$B,0))*INDEX('00_Control'!$C:$C,MATCH("Loans_Repricing",'00_Control'!$B:$B,0))*0.01)-(INDEX('01_RawData'!$B:$K,MATCH("Customer Deposits - Average",'01_RawData'!$A:$A,0),MATCH($A4,'01_RawData'!$B$1:$K$1,0))*INDEX('00_Control'!$C:$C,MATCH("Deposit_Beta",'00_Control'!$B:$B,0)) *INDEX('00_Control'!$C:$C,MATCH("Deposits_Repricing",'00_Control'!$B:$B,0))*0.01)-(INDEX('01_RawData'!$B:$K,MATCH("Wholesale Funding - Average",'01_RawData'!$A:$A,0),MATCH($A4,'01_RawData'!$B$1:$K$1,0))*INDEX('00_Control'!$C:$C,MATCH("Wholesale_Funding_Beta",'00_Control'!$B:$B,0)) *INDEX('00_Control'!$C:$C,MATCH("Funding_Repricing",'00_Control'!$B:$B,0)) *0.01) -> 625.6 | E4: =((($C4 + $D4) /INDEX('01_RawData'!$B:$K,MATCH("Average Interest-Earning Assets (AIEA)",'01_RawData'!$A:$A,0),MATCH($A4,'01_RawData'!$B$1:$K$1,0)))- $B4) * 10000 -> 14.348624 | F4: =D4 * (1 - INDEX('00_Control'!$C:$C, MATCH("Tax Rate", '00_Control'!$B:$B, 0))) -> 481.712 | G4: =-D4 -> -625.6 | H4: =((($C4 + $G4) /INDEX('01_RawData'!$B:$K,MATCH("Average Interest-Earning Assets (AIEA)",'01_RawData'!$A:$A,0),MATCH($A4,'01_RawData'!$B$1:$K$1,0)))- $B4) * 10000 -> -14.348624 | I4: =-F4 -> -481.712 | J4: =D4 * INDEX('00_Control'!$C:$C, MATCH("Hedge_Adjustment", '00_Control'!$B:$B, 0)) -> 375.36 | K4: =($J4 / INDEX('01_RawData'!$B:$K,MATCH("Average Interest-Earning Assets (AIEA)", '01_RawData'!$A:$A, 0),MATCH($A4, '01_RawData'!$B$1:$K$1, 0))) * 10000 -> 8.6091743 | L4: =F4 * INDEX('00_Control'!$C:$C, MATCH("Hedge_Adjustment", '00_Control'!$B:$B, 0)) -> 289.0272
A5: 2019 | B5: =INDEX('01_RawData'!$B:$K, MATCH("Reported Banking NIM", '01_RawData'!$A:$A, 0), MATCH($A5, '01_RawData'!$B$1:$K$1, 0)) -> 0.0288 | C5: =INDEX('01_RawData'!$B:$K, MATCH("Implied Banking NII", '01_RawData'!$A:$A, 0), MATCH($A5, '01_RawData'!$B$1:$K$1, 0)) -> 12528 | D5: =(INDEX('01_RawData'!$B:$K,MATCH("Loans - Average",'01_RawData'!$A:$A,0),MATCH($A5,'01_RawData'!$B$1:$K$1,0))*INDEX('00_Control'!$C:$C,MATCH("Loan_Beta",'00_Control'!$B:$B,0))*INDEX('00_Control'!$C:$C,MATCH("Loans_Repricing",'00_Control'!$B:$B,0))*0.01)-(INDEX('01_RawData'!$B:$K,MATCH("Customer Deposits - Average",'01_RawData'!$A:$A,0),MATCH($A5,'01_RawData'!$B$1:$K$1,0))*INDEX('00_Control'!$C:$C,MATCH("Deposit_Beta",'00_Control'!$B:$B,0)) *INDEX('00_Control'!$C:$C,MATCH("Deposits_Repricing",'00_Control'!$B:$B,0))*0.01)-(INDEX('01_RawData'!$B:$K,MATCH("Wholesale Funding - Average",'01_RawData'!$A:$A,0),MATCH($A5,'01_RawData'!$B$1:$K$1,0))*INDEX('00_Control'!$C:$C,MATCH("Wholesale_Funding_Beta",'00_Control'!$B:$B,0)) *INDEX('00_Control'!$C:$C,MATCH("Funding_Repricing",'00_Control'!$B:$B,0)) *0.01) -> 507.9 | E5: =((($C5 + $D5) /INDEX('01_RawData'!$B:$K,MATCH("Average Interest-Earning Assets (AIEA)",'01_RawData'!$A:$A,0),MATCH($A5,'01_RawData'!$B$1:$K$1,0)))- $B5) * 10000 -> 11.675862 | F5: =D5 * (1 - INDEX('00_Control'!$C:$C, MATCH("Tax Rate", '00_Control'!$B:$B, 0))) -> 391.083 | G5: =-D5 -> -507.9 | H5: =((($C5 + $G5) /INDEX('01_RawData'!$B:$K,MATCH("Average Interest-Earning Assets (AIEA)",'01_RawData'!$A:$A,0),MATCH($A5,'01_RawData'!$B$1:$K$1,0)))- $B5) * 10000 -> -11.675862 | I5: =-F5 -> -391.083 | J5: =D5 * INDEX('00_Control'!$C:$C, MATCH("Hedge_Adjustment", '00_Control'!$B:$B, 0)) -> 304.74 | K5: =($J5 / INDEX('01_RawData'!$B:$K,MATCH("Average Interest-Earning Assets (AIEA)", '01_RawData'!$A:$A, 0),MATCH($A5, '01_RawData'!$B$1:$K$1, 0))) * 10000 -> 7.0055172 | L5: =F5 * INDEX('00_Control'!$C:$C, MATCH("Hedge_Adjustment", '00_Control'!$B:$B, 0)) -> 234.6498
A6: 2020 | B6: =INDEX('01_RawData'!$B:$K, MATCH("Reported Banking NIM", '01_RawData'!$A:$A, 0), MATCH($A6, '01_RawData'!$B$1:$K$1, 0)) -> 0.0252 | C6: =INDEX('01_RawData'!$B:$K, MATCH("Implied Banking NII", '01_RawData'!$A:$A, 0), MATCH($A6, '01_RawData'!$B$1:$K$1, 0)) -> 10962 | D6: =(INDEX('01_RawData'!$B:$K,MATCH("Loans - Average",'01_RawData'!$A:$A,0),MATCH($A6,'01_RawData'!$B$1:$K$1,0))*INDEX('00_Control'!$C:$C,MATCH("Loan_Beta",'00_Control'!$B:$B,0))*INDEX('00_Control'!$C:$C,MATCH("Loans_Repricing",'00_Control'!$B:$B,0))*0.01)-(INDEX('01_RawData'!$B:$K,MATCH("Customer Deposits - Average",'01_RawData'!$A:$A,0),MATCH($A6,'01_RawData'!$B$1:$K$1,0))*INDEX('00_Control'!$C:$C,MATCH("Deposit_Beta",'00_Control'!$B:$B,0)) *INDEX('00_Control'!$C:$C,MATCH("Deposits_Repricing",'00_Control'!$B:$B,0))*0.01)-(INDEX('01_RawData'!$B:$K,MATCH("Wholesale Funding - Average",'01_RawData'!$A:$A,0),MATCH($A6,'01_RawData'!$B$1:$K$1,0))*INDEX('00_Control'!$C:$C,MATCH("Wholesale_Funding_Beta",'00_Control'!$B:$B,0)) *INDEX('00_Control'!$C:$C,MATCH("Funding_Repricing",'00_Control'!$B:$B,0)) *0.01) -> 516.635 | E6: =((($C6 + $D6) /INDEX('01_RawData'!$B:$K,MATCH("Average Interest-Earning Assets (AIEA)",'01_RawData'!$A:$A,0),MATCH($A6,'01_RawData'!$B$1:$K$1,0)))- $B6) * 10000 -> 11.876667 | F6: =D6 * (1 - INDEX('00_Control'!$C:$C, MATCH("Tax Rate", '00_Control'!$B:$B, 0))) -> 397.80895 | G6: =-D6 -> -516.635 | H6: =((($C6 + $G6) /INDEX('01_RawData'!$B:$K,MATCH("Average Interest-Earning Assets (AIEA)",'01_RawData'!$A:$A,0),MATCH($A6,'01_RawData'!$B$1:$K$1,0)))- $B6) * 10000 -> -11.876667 | I6: =-F6 -> -397.80895 | J6: =D6 * INDEX('00_Control'!$C:$C, MATCH("Hedge_Adjustment", '00_Control'!$B:$B, 0)) -> 309.981 | K6: =($J6 / INDEX('01_RawData'!$B:$K,MATCH("Average Interest-Earning Assets (AIEA)", '01_RawData'!$A:$A, 0),MATCH($A6, '01_RawData'!$B$1:$K$1, 0))) * 10000 -> 7.126 | L6: =F6 * INDEX('00_Control'!$C:$C, MATCH("Hedge_Adjustment", '00_Control'!$B:$B, 0)) -> 238.68537
A7: 2021 | B7: =INDEX('01_RawData'!$B:$K, MATCH("Reported Banking NIM", '01_RawData'!$A:$A, 0), MATCH($A7, '01_RawData'!$B$1:$K$1, 0)) -> 0.0254 | C7: =INDEX('01_RawData'!$B:$K, MATCH("Implied Banking NII", '01_RawData'!$A:$A, 0), MATCH($A7, '01_RawData'!$B$1:$K$1, 0)) -> 11303 | D7: =(INDEX('01_RawData'!$B:$K,MATCH("Loans - Average",'01_RawData'!$A:$A,0),MATCH($A7,'01_RawData'!$B$1:$K$1,0))*INDEX('00_Control'!$C:$C,MATCH("Loan_Beta",'00_Control'!$B:$B,0))*INDEX('00_Control'!$C:$C,MATCH("Loans_Repricing",'00_Control'!$B:$B,0))*0.01)-(INDEX('01_RawData'!$B:$K,MATCH("Customer Deposits - Average",'01_RawData'!$A:$A,0),MATCH($A7,'01_RawData'!$B$1:$K$1,0))*INDEX('00_Control'!$C:$C,MATCH("Deposit_Beta",'00_Control'!$B:$B,0)) *INDEX('00_Control'!$C:$C,MATCH("Deposits_Repricing",'00_Control'!$B:$B,0))*0.01)-(INDEX('01_RawData'!$B:$K,MATCH("Wholesale Funding - Average",'01_RawData'!$A:$A,0),MATCH($A7,'01_RawData'!$B$1:$K$1,0))*INDEX('00_Control'!$C:$C,MATCH("Wholesale_Funding_Beta",'00_Control'!$B:$B,0)) *INDEX('00_Control'!$C:$C,MATCH("Funding_Repricing",'00_Control'!$B:$B,0)) *0.01) -> 599.595 | E7: =((($C7 + $D7) /INDEX('01_RawData'!$B:$K,MATCH("Average Interest-Earning Assets (AIEA)",'01_RawData'!$A:$A,0),MATCH($A7,'01_RawData'!$B$1:$K$1,0)))- $B7) * 10000 -> 13.474045 | F7: =D7 * (1 - INDEX('00_Control'!$C:$C, MATCH("Tax Rate", '00_Control'!$B:$B, 0))) -> 461.68815 | G7: =-D7 -> -599.595 | H7: =((($C7 + $G7) /INDEX('01_RawData'!$B:$K,MATCH("Average Interest-Earning Assets (AIEA)",'01_RawData'!$A:$A,0),MATCH($A7,'01_RawData'!$B$1:$K$1,0)))- $B7) * 10000 -> -13.474045 | I7: =-F7 -> -461.68815 | J7: =D7 * INDEX('00_Control'!$C:$C, MATCH("Hedge_Adjustment", '00_Control'!$B:$B, 0)) -> 359.757 | K7: =($J7 / INDEX('01_RawData'!$B:$K,MATCH("Average Interest-Earning Assets (AIEA)", '01_RawData'!$A:$A, 0),MATCH($A7, '01_RawData'!$B$1:$K$1, 0))) * 10000 -> 8.084427 | L7: =F7 * INDEX('00_Control'!$C:$C, MATCH("Hedge_Adjustment", '00_Control'!$B:$B, 0)) -> 277.01289
A8: 2022 | B8: =INDEX('01_RawData'!$B:$K, MATCH("Reported Banking NIM", '01_RawData'!$A:$A, 0), MATCH($A8, '01_RawData'!$B$1:$K$1, 0)) -> 0.0294 | C8: =INDEX('01_RawData'!$B:$K, MATCH("Implied Banking NII", '01_RawData'!$A:$A, 0), MATCH($A8, '01_RawData'!$B$1:$K$1, 0)) -> 13288.8 | D8: =(INDEX('01_RawData'!$B:$K,MATCH("Loans - Average",'01_RawData'!$A:$A,0),MATCH($A8,'01_RawData'!$B$1:$K$1,0))*INDEX('00_Control'!$C:$C,MATCH("Loan_Beta",'00_Control'!$B:$B,0))*INDEX('00_Control'!$C:$C,MATCH("Loans_Repricing",'00_Control'!$B:$B,0))*0.01)-(INDEX('01_RawData'!$B:$K,MATCH("Customer Deposits - Average",'01_RawData'!$A:$A,0),MATCH($A8,'01_RawData'!$B$1:$K$1,0))*INDEX('00_Control'!$C:$C,MATCH("Deposit_Beta",'00_Control'!$B:$B,0)) *INDEX('00_Control'!$C:$C,MATCH("Deposits_Repricing",'00_Control'!$B:$B,0))*0.01)-(INDEX('01_RawData'!$B:$K,MATCH("Wholesale Funding - Average",'01_RawData'!$A:$A,0),MATCH($A8,'01_RawData'!$B$1:$K$1,0))*INDEX('00_Control'!$C:$C,MATCH("Wholesale_Funding_Beta",'00_Control'!$B:$B,0)) *INDEX('00_Control'!$C:$C,MATCH("Funding_Repricing",'00_Control'!$B:$B,0)) *0.01) -> 646.8525 | E8: =((($C8 + $D8) /INDEX('01_RawData'!$B:$K,MATCH("Average Interest-Earning Assets (AIEA)",'01_RawData'!$A:$A,0),MATCH($A8,'01_RawData'!$B$1:$K$1,0)))- $B8) * 10000 -> 14.310896 | F8: =D8 * (1 - INDEX('00_Control'!$C:$C, MATCH("Tax Rate", '00_Control'!$B:$B, 0))) -> 498.07643 | G8: =-D8 -> -646.8525 | H8: =((($C8 + $G8) /INDEX('01_RawData'!$B:$K,MATCH("Average Interest-Earning Assets (AIEA)",'01_RawData'!$A:$A,0),MATCH($A8,'01_RawData'!$B$1:$K$1,0)))- $B8) * 10000 -> -14.310896 | I8: =-F8 -> -498.07643 | J8: =D8 * INDEX('00_Control'!$C:$C, MATCH("Hedge_Adjustment", '00_Control'!$B:$B, 0)) -> 388.1115 | K8: =($J8 / INDEX('01_RawData'!$B:$K,MATCH("Average Interest-Earning Assets (AIEA)", '01_RawData'!$A:$A, 0),MATCH($A8, '01_RawData'!$B$1:$K$1, 0))) * 10000 -> 8.5865376 | L8: =F8 * INDEX('00_Control'!$C:$C, MATCH("Hedge_Adjustment", '00_Control'!$B:$B, 0)) -> 298.84586
A9: 2023 | B9: =INDEX('01_RawData'!$B:$K, MATCH("Reported Banking NIM", '01_RawData'!$A:$A, 0), MATCH($A9, '01_RawData'!$B$1:$K$1, 0)) -> 0.0311 | C9: =INDEX('01_RawData'!$B:$K, MATCH("Implied Banking NII", '01_RawData'!$A:$A, 0), MATCH($A9, '01_RawData'!$B$1:$K$1, 0)) -> 14097.63 | D9: =(INDEX('01_RawData'!$B:$K,MATCH("Loans - Average",'01_RawData'!$A:$A,0),MATCH($A9,'01_RawData'!$B$1:$K$1,0))*INDEX('00_Control'!$C:$C,MATCH("Loan_Beta",'00_Control'!$B:$B,0))*INDEX('00_Control'!$C:$C,MATCH("Loans_Repricing",'00_Control'!$B:$B,0))*0.01)-(INDEX('01_RawData'!$B:$K,MATCH("Customer Deposits - Average",'01_RawData'!$A:$A,0),MATCH($A9,'01_RawData'!$B$1:$K$1,0))*INDEX('00_Control'!$C:$C,MATCH("Deposit_Beta",'00_Control'!$B:$B,0)) *INDEX('00_Control'!$C:$C,MATCH("Deposits_Repricing",'00_Control'!$B:$B,0))*0.01)-(INDEX('01_RawData'!$B:$K,MATCH("Wholesale Funding - Average",'01_RawData'!$A:$A,0),MATCH($A9,'01_RawData'!$B$1:$K$1,0))*INDEX('00_Control'!$C:$C,MATCH("Wholesale_Funding_Beta",'00_Control'!$B:$B,0)) *INDEX('00_Control'!$C:$C,MATCH("Funding_Repricing",'00_Control'!$B:$B,0)) *0.01) -> 626.2775 | E9: =((($C9 + $D9) /INDEX('01_RawData'!$B:$K,MATCH("Average Interest-Earning Assets (AIEA)",'01_RawData'!$A:$A,0),MATCH($A9,'01_RawData'!$B$1:$K$1,0)))- $B9) * 10000 -> 13.815961 | F9: =D9 * (1 - INDEX('00_Control'!$C:$C, MATCH("Tax Rate", '00_Control'!$B:$B, 0))) -> 482.23367 | G9: =-D9 -> -626.2775 | H9: =((($C9 + $G9) /INDEX('01_RawData'!$B:$K,MATCH("Average Interest-Earning Assets (AIEA)",'01_RawData'!$A:$A,0),MATCH($A9,'01_RawData'!$B$1:$K$1,0)))- $B9) * 10000 -> -13.815961 | I9: =-F9 -> -482.23367 | J9: =D9 * INDEX('00_Control'!$C:$C, MATCH("Hedge_Adjustment", '00_Control'!$B:$B, 0)) -> 375.7665 | K9: =($J9 / INDEX('01_RawData'!$B:$K,MATCH("Average Interest-Earning Assets (AIEA)", '01_RawData'!$A:$A, 0),MATCH($A9, '01_RawData'!$B$1:$K$1, 0))) * 10000 -> 8.2895764 | L9: =F9 * INDEX('00_Control'!$C:$C, MATCH("Hedge_Adjustment", '00_Control'!$B:$B, 0)) -> 289.3402
A10: 2024 | B10: =INDEX('01_RawData'!$B:$K, MATCH("Reported Banking NIM", '01_RawData'!$A:$A, 0), MATCH($A10, '01_RawData'!$B$1:$K$1, 0)) -> 0.0295 | C10: =INDEX('01_RawData'!$B:$K, MATCH("Implied Banking NII", '01_RawData'!$A:$A, 0), MATCH($A10, '01_RawData'!$B$1:$K$1, 0)) -> 13310.4 | D10: =(INDEX('01_RawData'!$B:$K,MATCH("Loans - Average",'01_RawData'!$A:$A,0),MATCH($A10,'01_RawData'!$B$1:$K$1,0))*INDEX('00_Control'!$C:$C,MATCH("Loan_Beta",'00_Control'!$B:$B,0))*INDEX('00_Control'!$C:$C,MATCH("Loans_Repricing",'00_Control'!$B:$B,0))*0.01)-(INDEX('01_RawData'!$B:$K,MATCH("Customer Deposits - Average",'01_RawData'!$A:$A,0),MATCH($A10,'01_RawData'!$B$1:$K$1,0))*INDEX('00_Control'!$C:$C,MATCH("Deposit_Beta",'00_Control'!$B:$B,0)) *INDEX('00_Control'!$C:$C,MATCH("Deposits_Repricing",'00_Control'!$B:$B,0))*0.01)-(INDEX('01_RawData'!$B:$K,MATCH("Wholesale Funding - Average",'01_RawData'!$A:$A,0),MATCH($A10,'01_RawData'!$B$1:$K$1,0))*INDEX('00_Control'!$C:$C,MATCH("Wholesale_Funding_Beta",'00_Control'!$B:$B,0)) *INDEX('00_Control'!$C:$C,MATCH("Funding_Repricing",'00_Control'!$B:$B,0)) *0.01) -> 657.9625 | E10: =((($C10 + $D10) /INDEX('01_RawData'!$B:$K,MATCH("Average Interest-Earning Assets (AIEA)",'01_RawData'!$A:$A,0),MATCH($A10,'01_RawData'!$B$1:$K$1,0)))- $B10) * 10000 -> 14.582502 | F10: =D10 * (1 - INDEX('00_Control'!$C:$C, MATCH("Tax Rate", '00_Control'!$B:$B, 0))) -> 506.63112 | G10: =-D10 -> -657.9625 | H10: =((($C10 + $G10) /INDEX('01_RawData'!$B:$K,MATCH("Average Interest-Earning Assets (AIEA)",'01_RawData'!$A:$A,0),MATCH($A10,'01_RawData'!$B$1:$K$1,0)))- $B10) * 10000 -> -14.582502 | I10: =-F10 -> -506.63112 | J10: =D10 * INDEX('00_Control'!$C:$C, MATCH("Hedge_Adjustment", '00_Control'!$B:$B, 0)) -> 394.7775 | K10: =($J10 / INDEX('01_RawData'!$B:$K,MATCH("Average Interest-Earning Assets (AIEA)", '01_RawData'!$A:$A, 0),MATCH($A10, '01_RawData'!$B$1:$K$1, 0))) * 10000 -> 8.7495013 | L10: =F10 * INDEX('00_Control'!$C:$C, MATCH("Hedge_Adjustment", '00_Control'!$B:$B, 0)) -> 303.97867
A11: 2025 | B11: =INDEX('01_RawData'!$B:$K, MATCH("Reported Banking NIM", '01_RawData'!$A:$A, 0), MATCH($A11, '01_RawData'!$B$1:$K$1, 0)) -> 0.0306 | C11: =INDEX('01_RawData'!$B:$K, MATCH("Implied Banking NII", '01_RawData'!$A:$A, 0), MATCH($A11, '01_RawData'!$B$1:$K$1, 0)) -> 14164.74 | D11: =(INDEX('01_RawData'!$B:$K,MATCH("Loans - Average",'01_RawData'!$A:$A,0),MATCH($A11,'01_RawData'!$B$1:$K$1,0))*INDEX('00_Control'!$C:$C,MATCH("Loan_Beta",'00_Control'!$B:$B,0))*INDEX('00_Control'!$C:$C,MATCH("Loans_Repricing",'00_Control'!$B:$B,0))*0.01)-(INDEX('01_RawData'!$B:$K,MATCH("Customer Deposits - Average",'01_RawData'!$A:$A,0),MATCH($A11,'01_RawData'!$B$1:$K$1,0))*INDEX('00_Control'!$C:$C,MATCH("Deposit_Beta",'00_Control'!$B:$B,0)) *INDEX('00_Control'!$C:$C,MATCH("Deposits_Repricing",'00_Control'!$B:$B,0))*0.01)-(INDEX('01_RawData'!$B:$K,MATCH("Wholesale Funding - Average",'01_RawData'!$A:$A,0),MATCH($A11,'01_RawData'!$B$1:$K$1,0))*INDEX('00_Control'!$C:$C,MATCH("Wholesale_Funding_Beta",'00_Control'!$B:$B,0)) *INDEX('00_Control'!$C:$C,MATCH("Funding_Repricing",'00_Control'!$B:$B,0)) *0.01) -> 708.6 | E11: =((($C11 + $D11) /INDEX('01_RawData'!$B:$K,MATCH("Average Interest-Earning Assets (AIEA)",'01_RawData'!$A:$A,0),MATCH($A11,'01_RawData'!$B$1:$K$1,0)))- $B11) * 10000 -> 15.307842 | F11: =D11 * (1 - INDEX('00_Control'!$C:$C, MATCH("Tax Rate", '00_Control'!$B:$B, 0))) -> 545.622 | G11: =-D11 -> -708.6 | H11: =((($C11 + $G11) /INDEX('01_RawData'!$B:$K,MATCH("Average Interest-Earning Assets (AIEA)",'01_RawData'!$A:$A,0),MATCH($A11,'01_RawData'!$B$1:$K$1,0)))- $B11) * 10000 -> -15.307842 | I11: =-F11 -> -545.622 | J11: =D11 * INDEX('00_Control'!$C:$C, MATCH("Hedge_Adjustment", '00_Control'!$B:$B, 0)) -> 425.16 | K11: =($J11 / INDEX('01_RawData'!$B:$K,MATCH("Average Interest-Earning Assets (AIEA)", '01_RawData'!$A:$A, 0),MATCH($A11, '01_RawData'!$B$1:$K$1, 0))) * 10000 -> 9.1847051 | L11: =F11 * INDEX('00_Control'!$C:$C, MATCH("Hedge_Adjustment", '00_Control'!$B:$B, 0)) -> 327.3732
